[
    {
        "FormulaSequence": 1,
        "GlobalKey": "VPL-TransformNewAccountPrefCustoma1V3h000002X3QeEAKItem0",
        "IsDisabled": false,
        "IsRequiredForUpsert": false,
        "IsUpsertKey": false,
        "Name": "VPL-TransformNewAccountPref",
        "OmniDataTransformationId": {
            "Name": "VPL-TransformNewAccountPref",
            "VlocityDataPackType": "VlocityMatchingKeyObject",
            "VlocityMatchingRecordSourceKey": "OmniDataTransform/VPL-TransformNewAccountPref",
            "VlocityRecordSObjectType": "OmniDataTransform"
        },
        "OutputCreationSequence": 0,
        "OutputFieldName": "Formula",
        "OutputObjectName": "Formula",
        "VlocityDataPackType": "SObject",
        "VlocityRecordSObjectType": "OmniDataTransformItem"
    },
    {
        "GlobalKey": "VPL-TransformNewAccountPrefCustoma1V3h000002X3QeEAKItem1",
        "InputFieldName": "AccountNotificationPreference:AccountId",
        "IsDisabled": false,
        "IsRequiredForUpsert": false,
        "IsUpsertKey": false,
        "Name": "VPL-TransformNewAccountPref",
        "OmniDataTransformationId": {
            "Name": "VPL-TransformNewAccountPref",
            "VlocityDataPackType": "VlocityMatchingKeyObject",
            "VlocityMatchingRecordSourceKey": "OmniDataTransform/VPL-TransformNewAccountPref",
            "VlocityRecordSObjectType": "OmniDataTransform"
        },
        "OutputCreationSequence": 1,
        "OutputFieldName": "UpdatedAccountPref|1:AccountId",
        "OutputObjectName": "json",
        "VlocityDataPackType": "SObject",
        "VlocityRecordSObjectType": "OmniDataTransformItem"
    },
    {
        "GlobalKey": "VPL-TransformNewAccountPrefCustoma1V3h000002X3QeEAKItem8",
        "InputFieldName": "AccountNotificationPreference:AccountName",
        "IsDisabled": false,
        "IsRequiredForUpsert": false,
        "IsUpsertKey": false,
        "Name": "VPL-TransformNewAccountPref",
        "OmniDataTransformationId": {
            "Name": "VPL-TransformNewAccountPref",
            "VlocityDataPackType": "VlocityMatchingKeyObject",
            "VlocityMatchingRecordSourceKey": "OmniDataTransform/VPL-TransformNewAccountPref",
            "VlocityRecordSObjectType": "OmniDataTransform"
        },
        "OutputCreationSequence": 1,
        "OutputFieldName": "UpdatedAccountPref|1:AccountName",
        "OutputObjectName": "json",
        "VlocityDataPackType": "SObject",
        "VlocityRecordSObjectType": "OmniDataTransformItem"
    },
    {
        "DefaultValue": "None",
        "GlobalKey": "VPL-TransformNewAccountPrefCustoma1V3h000002X3QeEAKItem36",
        "InputFieldName": "ManageNotificationPreferences:BillNotifications",
        "IsDisabled": false,
        "IsRequiredForUpsert": false,
        "IsUpsertKey": false,
        "Name": "VPL-TransformNewAccountPref",
        "OmniDataTransformationId": {
            "Name": "VPL-TransformNewAccountPref",
            "VlocityDataPackType": "VlocityMatchingKeyObject",
            "VlocityMatchingRecordSourceKey": "OmniDataTransform/VPL-TransformNewAccountPref",
            "VlocityRecordSObjectType": "OmniDataTransform"
        },
        "OutputCreationSequence": 1,
        "OutputFieldName": "UpdatedAccountPref|1:AttrValue",
        "OutputObjectName": "json",
        "VlocityDataPackType": "SObject",
        "VlocityRecordSObjectType": "OmniDataTransformItem"
    },
    {
        "GlobalKey": "VPL-TransformNewAccountPrefCustoma1V3h000002X3QeEAKItem16",
        "InputFieldName": "Category:BillNotifications:CategoryCode",
        "IsDisabled": false,
        "IsRequiredForUpsert": false,
        "IsUpsertKey": false,
        "Name": "VPL-TransformNewAccountPref",
        "OmniDataTransformationId": {
            "Name": "VPL-TransformNewAccountPref",
            "VlocityDataPackType": "VlocityMatchingKeyObject",
            "VlocityMatchingRecordSourceKey": "OmniDataTransform/VPL-TransformNewAccountPref",
            "VlocityRecordSObjectType": "OmniDataTransform"
        },
        "OutputCreationSequence": 1,
        "OutputFieldName": "UpdatedAccountPref|1:CategoryCode",
        "OutputObjectName": "json",
        "VlocityDataPackType": "SObject",
        "VlocityRecordSObjectType": "OmniDataTransformItem"
    },
    {
        "GlobalKey": "VPL-TransformNewAccountPrefCustoma1V3h000002X3QeEAKItem17",
        "InputFieldName": "Category:BillNotifications:CategoryId",
        "IsDisabled": false,
        "IsRequiredForUpsert": false,
        "IsUpsertKey": false,
        "Name": "VPL-TransformNewAccountPref",
        "OmniDataTransformationId": {
            "Name": "VPL-TransformNewAccountPref",
            "VlocityDataPackType": "VlocityMatchingKeyObject",
            "VlocityMatchingRecordSourceKey": "OmniDataTransform/VPL-TransformNewAccountPref",
            "VlocityRecordSObjectType": "OmniDataTransform"
        },
        "OutputCreationSequence": 1,
        "OutputFieldName": "UpdatedAccountPref|1:CategoryId",
        "OutputObjectName": "json",
        "VlocityDataPackType": "SObject",
        "VlocityRecordSObjectType": "OmniDataTransformItem"
    },
    {
        "GlobalKey": "VPL-TransformNewAccountPrefCustoma1V3h000002X3QeEAKItem7",
        "InputFieldName": "AccountNotificationPreference:AccountId",
        "IsDisabled": false,
        "IsRequiredForUpsert": false,
        "IsUpsertKey": false,
        "Name": "VPL-TransformNewAccountPref",
        "OmniDataTransformationId": {
            "Name": "VPL-TransformNewAccountPref",
            "VlocityDataPackType": "VlocityMatchingKeyObject",
            "VlocityMatchingRecordSourceKey": "OmniDataTransform/VPL-TransformNewAccountPref",
            "VlocityRecordSObjectType": "OmniDataTransform"
        },
        "OutputCreationSequence": 1,
        "OutputFieldName": "UpdatedAccountPref|2:AccountId",
        "OutputObjectName": "json",
        "VlocityDataPackType": "SObject",
        "VlocityRecordSObjectType": "OmniDataTransformItem"
    },
    {
        "GlobalKey": "VPL-TransformNewAccountPrefCustoma1V3h000002X3QeEAKItem14",
        "InputFieldName": "AccountNotificationPreference:AccountName",
        "IsDisabled": false,
        "IsRequiredForUpsert": false,
        "IsUpsertKey": false,
        "Name": "VPL-TransformNewAccountPref",
        "OmniDataTransformationId": {
            "Name": "VPL-TransformNewAccountPref",
            "VlocityDataPackType": "VlocityMatchingKeyObject",
            "VlocityMatchingRecordSourceKey": "OmniDataTransform/VPL-TransformNewAccountPref",
            "VlocityRecordSObjectType": "OmniDataTransform"
        },
        "OutputCreationSequence": 1,
        "OutputFieldName": "UpdatedAccountPref|2:AccountName",
        "OutputObjectName": "json",
        "VlocityDataPackType": "SObject",
        "VlocityRecordSObjectType": "OmniDataTransformItem"
    },
    {
        "GlobalKey": "VPL-TransformNewAccountPrefCustoma1V3h000002X3QeEAKItem30",
        "InputFieldName": "Category:PaymentReminders:AttrAssignId",
        "IsDisabled": false,
        "IsRequiredForUpsert": false,
        "IsUpsertKey": false,
        "Name": "VPL-TransformNewAccountPref",
        "OmniDataTransformationId": {
            "Name": "VPL-TransformNewAccountPref",
            "VlocityDataPackType": "VlocityMatchingKeyObject",
            "VlocityMatchingRecordSourceKey": "OmniDataTransform/VPL-TransformNewAccountPref",
            "VlocityRecordSObjectType": "OmniDataTransform"
        },
        "OutputCreationSequence": 1,
        "OutputFieldName": "UpdatedAccountPref|2:AttrAssignId",
        "OutputObjectName": "json",
        "VlocityDataPackType": "SObject",
        "VlocityRecordSObjectType": "OmniDataTransformItem"
    },
    {
        "DefaultValue": "None",
        "GlobalKey": "VPL-TransformNewAccountPrefCustoma1V3h000002X3QeEAKItem41",
        "InputFieldName": "ManageNotificationPreferences:PaymentRemindersNotifications",
        "IsDisabled": false,
        "IsRequiredForUpsert": false,
        "IsUpsertKey": false,
        "Name": "VPL-TransformNewAccountPref",
        "OmniDataTransformationId": {
            "Name": "VPL-TransformNewAccountPref",
            "VlocityDataPackType": "VlocityMatchingKeyObject",
            "VlocityMatchingRecordSourceKey": "OmniDataTransform/VPL-TransformNewAccountPref",
            "VlocityRecordSObjectType": "OmniDataTransform"
        },
        "OutputCreationSequence": 1,
        "OutputFieldName": "UpdatedAccountPref|2:AttrValue",
        "OutputObjectName": "json",
        "VlocityDataPackType": "SObject",
        "VlocityRecordSObjectType": "OmniDataTransformItem"
    },
    {
        "GlobalKey": "VPL-TransformNewAccountPrefCustoma1V3h000002X3QeEAKItem31",
        "InputFieldName": "Category:PaymentReminders:CategoryCode",
        "IsDisabled": false,
        "IsRequiredForUpsert": false,
        "IsUpsertKey": false,
        "Name": "VPL-TransformNewAccountPref",
        "OmniDataTransformationId": {
            "Name": "VPL-TransformNewAccountPref",
            "VlocityDataPackType": "VlocityMatchingKeyObject",
            "VlocityMatchingRecordSourceKey": "OmniDataTransform/VPL-TransformNewAccountPref",
            "VlocityRecordSObjectType": "OmniDataTransform"
        },
        "OutputCreationSequence": 1,
        "OutputFieldName": "UpdatedAccountPref|2:CategoryCode",
        "OutputObjectName": "json",
        "VlocityDataPackType": "SObject",
        "VlocityRecordSObjectType": "OmniDataTransformItem"
    },
    {
        "GlobalKey": "VPL-TransformNewAccountPrefCustoma1V3h000002X3QeEAKItem32",
        "InputFieldName": "Category:PaymentReminders:CategoryId",
        "IsDisabled": false,
        "IsRequiredForUpsert": false,
        "IsUpsertKey": false,
        "Name": "VPL-TransformNewAccountPref",
        "OmniDataTransformationId": {
            "Name": "VPL-TransformNewAccountPref",
            "VlocityDataPackType": "VlocityMatchingKeyObject",
            "VlocityMatchingRecordSourceKey": "OmniDataTransform/VPL-TransformNewAccountPref",
            "VlocityRecordSObjectType": "OmniDataTransform"
        },
        "OutputCreationSequence": 1,
        "OutputFieldName": "UpdatedAccountPref|2:CategoryId",
        "OutputObjectName": "json",
        "VlocityDataPackType": "SObject",
        "VlocityRecordSObjectType": "OmniDataTransformItem"
    },
    {
        "GlobalKey": "VPL-TransformNewAccountPrefCustoma1V3h000002X3QeEAKItem6",
        "InputFieldName": "AccountNotificationPreference:AccountId",
        "IsDisabled": false,
        "IsRequiredForUpsert": false,
        "IsUpsertKey": false,
        "Name": "VPL-TransformNewAccountPref",
        "OmniDataTransformationId": {
            "Name": "VPL-TransformNewAccountPref",
            "VlocityDataPackType": "VlocityMatchingKeyObject",
            "VlocityMatchingRecordSourceKey": "OmniDataTransform/VPL-TransformNewAccountPref",
            "VlocityRecordSObjectType": "OmniDataTransform"
        },
        "OutputCreationSequence": 1,
        "OutputFieldName": "UpdatedAccountPref|3:AccountId",
        "OutputObjectName": "json",
        "VlocityDataPackType": "SObject",
        "VlocityRecordSObjectType": "OmniDataTransformItem"
    },
    {
        "GlobalKey": "VPL-TransformNewAccountPrefCustoma1V3h000002X3QeEAKItem13",
        "InputFieldName": "AccountNotificationPreference:AccountName",
        "IsDisabled": false,
        "IsRequiredForUpsert": false,
        "IsUpsertKey": false,
        "Name": "VPL-TransformNewAccountPref",
        "OmniDataTransformationId": {
            "Name": "VPL-TransformNewAccountPref",
            "VlocityDataPackType": "VlocityMatchingKeyObject",
            "VlocityMatchingRecordSourceKey": "OmniDataTransform/VPL-TransformNewAccountPref",
            "VlocityRecordSObjectType": "OmniDataTransform"
        },
        "OutputCreationSequence": 1,
        "OutputFieldName": "UpdatedAccountPref|3:AccountName",
        "OutputObjectName": "json",
        "VlocityDataPackType": "SObject",
        "VlocityRecordSObjectType": "OmniDataTransformItem"
    },
    {
        "DefaultValue": "None",
        "GlobalKey": "VPL-TransformNewAccountPrefCustoma1V3h000002X3QeEAKItem40",
        "InputFieldName": "ManageNotificationPreferences:OutageNotifications",
        "IsDisabled": false,
        "IsRequiredForUpsert": false,
        "IsUpsertKey": false,
        "Name": "VPL-TransformNewAccountPref",
        "OmniDataTransformationId": {
            "Name": "VPL-TransformNewAccountPref",
            "VlocityDataPackType": "VlocityMatchingKeyObject",
            "VlocityMatchingRecordSourceKey": "OmniDataTransform/VPL-TransformNewAccountPref",
            "VlocityRecordSObjectType": "OmniDataTransform"
        },
        "OutputCreationSequence": 1,
        "OutputFieldName": "UpdatedAccountPref|3:AttrValue",
        "OutputObjectName": "json",
        "VlocityDataPackType": "SObject",
        "VlocityRecordSObjectType": "OmniDataTransformItem"
    },
    {
        "GlobalKey": "VPL-TransformNewAccountPrefCustoma1V3h000002X3QeEAKItem28",
        "InputFieldName": "Category:OutageNotifications:CategoryCode",
        "IsDisabled": false,
        "IsRequiredForUpsert": false,
        "IsUpsertKey": false,
        "Name": "VPL-TransformNewAccountPref",
        "OmniDataTransformationId": {
            "Name": "VPL-TransformNewAccountPref",
            "VlocityDataPackType": "VlocityMatchingKeyObject",
            "VlocityMatchingRecordSourceKey": "OmniDataTransform/VPL-TransformNewAccountPref",
            "VlocityRecordSObjectType": "OmniDataTransform"
        },
        "OutputCreationSequence": 1,
        "OutputFieldName": "UpdatedAccountPref|3:CategoryCode",
        "OutputObjectName": "json",
        "VlocityDataPackType": "SObject",
        "VlocityRecordSObjectType": "OmniDataTransformItem"
    },
    {
        "GlobalKey": "VPL-TransformNewAccountPrefCustoma1V3h000002X3QeEAKItem29",
        "InputFieldName": "Category:OutageNotifications:CategoryId",
        "IsDisabled": false,
        "IsRequiredForUpsert": false,
        "IsUpsertKey": false,
        "Name": "VPL-TransformNewAccountPref",
        "OmniDataTransformationId": {
            "Name": "VPL-TransformNewAccountPref",
            "VlocityDataPackType": "VlocityMatchingKeyObject",
            "VlocityMatchingRecordSourceKey": "OmniDataTransform/VPL-TransformNewAccountPref",
            "VlocityRecordSObjectType": "OmniDataTransform"
        },
        "OutputCreationSequence": 1,
        "OutputFieldName": "UpdatedAccountPref|3:CategoryId",
        "OutputObjectName": "json",
        "VlocityDataPackType": "SObject",
        "VlocityRecordSObjectType": "OmniDataTransformItem"
    },
    {
        "GlobalKey": "VPL-TransformNewAccountPrefCustoma1V3h000002X3QeEAKItem5",
        "InputFieldName": "AccountNotificationPreference:AccountId",
        "IsDisabled": false,
        "IsRequiredForUpsert": false,
        "IsUpsertKey": false,
        "Name": "VPL-TransformNewAccountPref",
        "OmniDataTransformationId": {
            "Name": "VPL-TransformNewAccountPref",
            "VlocityDataPackType": "VlocityMatchingKeyObject",
            "VlocityMatchingRecordSourceKey": "OmniDataTransform/VPL-TransformNewAccountPref",
            "VlocityRecordSObjectType": "OmniDataTransform"
        },
        "OutputCreationSequence": 1,
        "OutputFieldName": "UpdatedAccountPref|4:AccountId",
        "OutputObjectName": "json",
        "VlocityDataPackType": "SObject",
        "VlocityRecordSObjectType": "OmniDataTransformItem"
    },
    {
        "GlobalKey": "VPL-TransformNewAccountPrefCustoma1V3h000002X3QeEAKItem12",
        "InputFieldName": "AccountNotificationPreference:AccountName",
        "IsDisabled": false,
        "IsRequiredForUpsert": false,
        "IsUpsertKey": false,
        "Name": "VPL-TransformNewAccountPref",
        "OmniDataTransformationId": {
            "Name": "VPL-TransformNewAccountPref",
            "VlocityDataPackType": "VlocityMatchingKeyObject",
            "VlocityMatchingRecordSourceKey": "OmniDataTransform/VPL-TransformNewAccountPref",
            "VlocityRecordSObjectType": "OmniDataTransform"
        },
        "OutputCreationSequence": 1,
        "OutputFieldName": "UpdatedAccountPref|4:AccountName",
        "OutputObjectName": "json",
        "VlocityDataPackType": "SObject",
        "VlocityRecordSObjectType": "OmniDataTransformItem"
    },
    {
        "DefaultValue": "None",
        "GlobalKey": "VPL-TransformNewAccountPrefCustoma1V3h000002X3QeEAKItem39",
        "InputFieldName": "ManageNotificationPreferences:OffersPromotions",
        "IsDisabled": false,
        "IsRequiredForUpsert": false,
        "IsUpsertKey": false,
        "Name": "VPL-TransformNewAccountPref",
        "OmniDataTransformationId": {
            "Name": "VPL-TransformNewAccountPref",
            "VlocityDataPackType": "VlocityMatchingKeyObject",
            "VlocityMatchingRecordSourceKey": "OmniDataTransform/VPL-TransformNewAccountPref",
            "VlocityRecordSObjectType": "OmniDataTransform"
        },
        "OutputCreationSequence": 1,
        "OutputFieldName": "UpdatedAccountPref|4:AttrValue",
        "OutputObjectName": "json",
        "VlocityDataPackType": "SObject",
        "VlocityRecordSObjectType": "OmniDataTransformItem"
    },
    {
        "GlobalKey": "VPL-TransformNewAccountPrefCustoma1V3h000002X3QeEAKItem25",
        "InputFieldName": "Category:OffersPromotions:CategoryCode",
        "IsDisabled": false,
        "IsRequiredForUpsert": false,
        "IsUpsertKey": false,
        "Name": "VPL-TransformNewAccountPref",
        "OmniDataTransformationId": {
            "Name": "VPL-TransformNewAccountPref",
            "VlocityDataPackType": "VlocityMatchingKeyObject",
            "VlocityMatchingRecordSourceKey": "OmniDataTransform/VPL-TransformNewAccountPref",
            "VlocityRecordSObjectType": "OmniDataTransform"
        },
        "OutputCreationSequence": 1,
        "OutputFieldName": "UpdatedAccountPref|4:CategoryCode",
        "OutputObjectName": "json",
        "VlocityDataPackType": "SObject",
        "VlocityRecordSObjectType": "OmniDataTransformItem"
    },
    {
        "GlobalKey": "VPL-TransformNewAccountPrefCustoma1V3h000002X3QeEAKItem26",
        "InputFieldName": "Category:OffersPromotions:CategoryId",
        "IsDisabled": false,
        "IsRequiredForUpsert": false,
        "IsUpsertKey": false,
        "Name": "VPL-TransformNewAccountPref",
        "OmniDataTransformationId": {
            "Name": "VPL-TransformNewAccountPref",
            "VlocityDataPackType": "VlocityMatchingKeyObject",
            "VlocityMatchingRecordSourceKey": "OmniDataTransform/VPL-TransformNewAccountPref",
            "VlocityRecordSObjectType": "OmniDataTransform"
        },
        "OutputCreationSequence": 1,
        "OutputFieldName": "UpdatedAccountPref|4:CategoryId",
        "OutputObjectName": "json",
        "VlocityDataPackType": "SObject",
        "VlocityRecordSObjectType": "OmniDataTransformItem"
    },
    {
        "GlobalKey": "VPL-TransformNewAccountPrefCustoma1V3h000002X3QeEAKItem4",
        "InputFieldName": "AccountNotificationPreference:AccountId",
        "IsDisabled": false,
        "IsRequiredForUpsert": false,
        "IsUpsertKey": false,
        "Name": "VPL-TransformNewAccountPref",
        "OmniDataTransformationId": {
            "Name": "VPL-TransformNewAccountPref",
            "VlocityDataPackType": "VlocityMatchingKeyObject",
            "VlocityMatchingRecordSourceKey": "OmniDataTransform/VPL-TransformNewAccountPref",
            "VlocityRecordSObjectType": "OmniDataTransform"
        },
        "OutputCreationSequence": 1,
        "OutputFieldName": "UpdatedAccountPref|5:AccountId",
        "OutputObjectName": "json",
        "VlocityDataPackType": "SObject",
        "VlocityRecordSObjectType": "OmniDataTransformItem"
    },
    {
        "GlobalKey": "VPL-TransformNewAccountPrefCustoma1V3h000002X3QeEAKItem11",
        "InputFieldName": "AccountNotificationPreference:AccountName",
        "IsDisabled": false,
        "IsRequiredForUpsert": false,
        "IsUpsertKey": false,
        "Name": "VPL-TransformNewAccountPref",
        "OmniDataTransformationId": {
            "Name": "VPL-TransformNewAccountPref",
            "VlocityDataPackType": "VlocityMatchingKeyObject",
            "VlocityMatchingRecordSourceKey": "OmniDataTransform/VPL-TransformNewAccountPref",
            "VlocityRecordSObjectType": "OmniDataTransform"
        },
        "OutputCreationSequence": 1,
        "OutputFieldName": "UpdatedAccountPref|5:AccountName",
        "OutputObjectName": "json",
        "VlocityDataPackType": "SObject",
        "VlocityRecordSObjectType": "OmniDataTransformItem"
    },
    {
        "DefaultValue": "None",
        "GlobalKey": "VPL-TransformNewAccountPrefCustoma1V3h000002X3QeEAKItem42",
        "InputFieldName": "ManageNotificationPreferences:WorkOrderNotifications",
        "IsDisabled": false,
        "IsRequiredForUpsert": false,
        "IsUpsertKey": false,
        "Name": "VPL-TransformNewAccountPref",
        "OmniDataTransformationId": {
            "Name": "VPL-TransformNewAccountPref",
            "VlocityDataPackType": "VlocityMatchingKeyObject",
            "VlocityMatchingRecordSourceKey": "OmniDataTransform/VPL-TransformNewAccountPref",
            "VlocityRecordSObjectType": "OmniDataTransform"
        },
        "OutputCreationSequence": 1,
        "OutputFieldName": "UpdatedAccountPref|5:AttrValue",
        "OutputObjectName": "json",
        "VlocityDataPackType": "SObject",
        "VlocityRecordSObjectType": "OmniDataTransformItem"
    },
    {
        "GlobalKey": "VPL-TransformNewAccountPrefCustoma1V3h000002X3QeEAKItem34",
        "InputFieldName": "Category:WorkorderNotifications:CategoryCode",
        "IsDisabled": false,
        "IsRequiredForUpsert": false,
        "IsUpsertKey": false,
        "Name": "VPL-TransformNewAccountPref",
        "OmniDataTransformationId": {
            "Name": "VPL-TransformNewAccountPref",
            "VlocityDataPackType": "VlocityMatchingKeyObject",
            "VlocityMatchingRecordSourceKey": "OmniDataTransform/VPL-TransformNewAccountPref",
            "VlocityRecordSObjectType": "OmniDataTransform"
        },
        "OutputCreationSequence": 1,
        "OutputFieldName": "UpdatedAccountPref|5:CategoryCode",
        "OutputObjectName": "json",
        "VlocityDataPackType": "SObject",
        "VlocityRecordSObjectType": "OmniDataTransformItem"
    },
    {
        "GlobalKey": "VPL-TransformNewAccountPrefCustoma1V3h000002X3QeEAKItem35",
        "InputFieldName": "Category:WorkorderNotifications:CategoryId",
        "IsDisabled": false,
        "IsRequiredForUpsert": false,
        "IsUpsertKey": false,
        "Name": "VPL-TransformNewAccountPref",
        "OmniDataTransformationId": {
            "Name": "VPL-TransformNewAccountPref",
            "VlocityDataPackType": "VlocityMatchingKeyObject",
            "VlocityMatchingRecordSourceKey": "OmniDataTransform/VPL-TransformNewAccountPref",
            "VlocityRecordSObjectType": "OmniDataTransform"
        },
        "OutputCreationSequence": 1,
        "OutputFieldName": "UpdatedAccountPref|5:CategoryId",
        "OutputObjectName": "json",
        "VlocityDataPackType": "SObject",
        "VlocityRecordSObjectType": "OmniDataTransformItem"
    },
    {
        "GlobalKey": "VPL-TransformNewAccountPrefCustoma1V3h000002X3QeEAKItem3",
        "InputFieldName": "AccountNotificationPreference:AccountId",
        "IsDisabled": false,
        "IsRequiredForUpsert": false,
        "IsUpsertKey": false,
        "Name": "VPL-TransformNewAccountPref",
        "OmniDataTransformationId": {
            "Name": "VPL-TransformNewAccountPref",
            "VlocityDataPackType": "VlocityMatchingKeyObject",
            "VlocityMatchingRecordSourceKey": "OmniDataTransform/VPL-TransformNewAccountPref",
            "VlocityRecordSObjectType": "OmniDataTransform"
        },
        "OutputCreationSequence": 1,
        "OutputFieldName": "UpdatedAccountPref|6:AccountId",
        "OutputObjectName": "json",
        "VlocityDataPackType": "SObject",
        "VlocityRecordSObjectType": "OmniDataTransformItem"
    },
    {
        "GlobalKey": "VPL-TransformNewAccountPrefCustoma1V3h000002X3QeEAKItem10",
        "InputFieldName": "AccountNotificationPreference:AccountName",
        "IsDisabled": false,
        "IsRequiredForUpsert": false,
        "IsUpsertKey": false,
        "Name": "VPL-TransformNewAccountPref",
        "OmniDataTransformationId": {
            "Name": "VPL-TransformNewAccountPref",
            "VlocityDataPackType": "VlocityMatchingKeyObject",
            "VlocityMatchingRecordSourceKey": "OmniDataTransform/VPL-TransformNewAccountPref",
            "VlocityRecordSObjectType": "OmniDataTransform"
        },
        "OutputCreationSequence": 1,
        "OutputFieldName": "UpdatedAccountPref|6:AccountName",
        "OutputObjectName": "json",
        "VlocityDataPackType": "SObject",
        "VlocityRecordSObjectType": "OmniDataTransformItem"
    },
    {
        "DefaultValue": "None",
        "GlobalKey": "VPL-TransformNewAccountPrefCustoma1V3h000002X3QeEAKItem37",
        "InputFieldName": "ManageNotificationPreferences:DNCFrom",
        "IsDisabled": false,
        "IsRequiredForUpsert": false,
        "IsUpsertKey": false,
        "Name": "VPL-TransformNewAccountPref",
        "OmniDataTransformationId": {
            "Name": "VPL-TransformNewAccountPref",
            "VlocityDataPackType": "VlocityMatchingKeyObject",
            "VlocityMatchingRecordSourceKey": "OmniDataTransform/VPL-TransformNewAccountPref",
            "VlocityRecordSObjectType": "OmniDataTransform"
        },
        "OutputCreationSequence": 1,
        "OutputFieldName": "UpdatedAccountPref|6:AttrValue",
        "OutputObjectName": "json",
        "VlocityDataPackType": "SObject",
        "VlocityRecordSObjectType": "OmniDataTransformItem"
    },
    {
        "GlobalKey": "VPL-TransformNewAccountPrefCustoma1V3h000002X3QeEAKItem19",
        "InputFieldName": "Category:DNCFrom:CategoryCode",
        "IsDisabled": false,
        "IsRequiredForUpsert": false,
        "IsUpsertKey": false,
        "Name": "VPL-TransformNewAccountPref",
        "OmniDataTransformationId": {
            "Name": "VPL-TransformNewAccountPref",
            "VlocityDataPackType": "VlocityMatchingKeyObject",
            "VlocityMatchingRecordSourceKey": "OmniDataTransform/VPL-TransformNewAccountPref",
            "VlocityRecordSObjectType": "OmniDataTransform"
        },
        "OutputCreationSequence": 1,
        "OutputFieldName": "UpdatedAccountPref|6:CategoryCode",
        "OutputObjectName": "json",
        "VlocityDataPackType": "SObject",
        "VlocityRecordSObjectType": "OmniDataTransformItem"
    },
    {
        "GlobalKey": "VPL-TransformNewAccountPrefCustoma1V3h000002X3QeEAKItem20",
        "InputFieldName": "Category:DNCFrom:CategoryId",
        "IsDisabled": false,
        "IsRequiredForUpsert": false,
        "IsUpsertKey": false,
        "Name": "VPL-TransformNewAccountPref",
        "OmniDataTransformationId": {
            "Name": "VPL-TransformNewAccountPref",
            "VlocityDataPackType": "VlocityMatchingKeyObject",
            "VlocityMatchingRecordSourceKey": "OmniDataTransform/VPL-TransformNewAccountPref",
            "VlocityRecordSObjectType": "OmniDataTransform"
        },
        "OutputCreationSequence": 1,
        "OutputFieldName": "UpdatedAccountPref|6:CategoryId",
        "OutputObjectName": "json",
        "VlocityDataPackType": "SObject",
        "VlocityRecordSObjectType": "OmniDataTransformItem"
    },
    {
        "GlobalKey": "VPL-TransformNewAccountPrefCustoma1V3h000002X3QeEAKItem2",
        "InputFieldName": "AccountNotificationPreference:AccountId",
        "IsDisabled": false,
        "IsRequiredForUpsert": false,
        "IsUpsertKey": false,
        "Name": "VPL-TransformNewAccountPref",
        "OmniDataTransformationId": {
            "Name": "VPL-TransformNewAccountPref",
            "VlocityDataPackType": "VlocityMatchingKeyObject",
            "VlocityMatchingRecordSourceKey": "OmniDataTransform/VPL-TransformNewAccountPref",
            "VlocityRecordSObjectType": "OmniDataTransform"
        },
        "OutputCreationSequence": 1,
        "OutputFieldName": "UpdatedAccountPref|7:AccountId",
        "OutputObjectName": "json",
        "VlocityDataPackType": "SObject",
        "VlocityRecordSObjectType": "OmniDataTransformItem"
    },
    {
        "GlobalKey": "VPL-TransformNewAccountPrefCustoma1V3h000002X3QeEAKItem9",
        "InputFieldName": "AccountNotificationPreference:AccountName",
        "IsDisabled": false,
        "IsRequiredForUpsert": false,
        "IsUpsertKey": false,
        "Name": "VPL-TransformNewAccountPref",
        "OmniDataTransformationId": {
            "Name": "VPL-TransformNewAccountPref",
            "VlocityDataPackType": "VlocityMatchingKeyObject",
            "VlocityMatchingRecordSourceKey": "OmniDataTransform/VPL-TransformNewAccountPref",
            "VlocityRecordSObjectType": "OmniDataTransform"
        },
        "OutputCreationSequence": 1,
        "OutputFieldName": "UpdatedAccountPref|7:AccountName",
        "OutputObjectName": "json",
        "VlocityDataPackType": "SObject",
        "VlocityRecordSObjectType": "OmniDataTransformItem"
    },
    {
        "DefaultValue": "None",
        "GlobalKey": "VPL-TransformNewAccountPrefCustoma1V3h000002X3QeEAKItem38",
        "InputFieldName": "ManageNotificationPreferences:DNCTo",
        "IsDisabled": false,
        "IsRequiredForUpsert": false,
        "IsUpsertKey": false,
        "Name": "VPL-TransformNewAccountPref",
        "OmniDataTransformationId": {
            "Name": "VPL-TransformNewAccountPref",
            "VlocityDataPackType": "VlocityMatchingKeyObject",
            "VlocityMatchingRecordSourceKey": "OmniDataTransform/VPL-TransformNewAccountPref",
            "VlocityRecordSObjectType": "OmniDataTransform"
        },
        "OutputCreationSequence": 1,
        "OutputFieldName": "UpdatedAccountPref|7:AttrValue",
        "OutputObjectName": "json",
        "VlocityDataPackType": "SObject",
        "VlocityRecordSObjectType": "OmniDataTransformItem"
    },
    {
        "GlobalKey": "VPL-TransformNewAccountPrefCustoma1V3h000002X3QeEAKItem22",
        "InputFieldName": "Category:DNCTo:CategoryCode",
        "IsDisabled": false,
        "IsRequiredForUpsert": false,
        "IsUpsertKey": false,
        "Name": "VPL-TransformNewAccountPref",
        "OmniDataTransformationId": {
            "Name": "VPL-TransformNewAccountPref",
            "VlocityDataPackType": "VlocityMatchingKeyObject",
            "VlocityMatchingRecordSourceKey": "OmniDataTransform/VPL-TransformNewAccountPref",
            "VlocityRecordSObjectType": "OmniDataTransform"
        },
        "OutputCreationSequence": 1,
        "OutputFieldName": "UpdatedAccountPref|7:CategoryCode",
        "OutputObjectName": "json",
        "VlocityDataPackType": "SObject",
        "VlocityRecordSObjectType": "OmniDataTransformItem"
    },
    {
        "GlobalKey": "VPL-TransformNewAccountPrefCustoma1V3h000002X3QeEAKItem23",
        "InputFieldName": "Category:DNCTo:CategoryId",
        "IsDisabled": false,
        "IsRequiredForUpsert": false,
        "IsUpsertKey": false,
        "Name": "VPL-TransformNewAccountPref",
        "OmniDataTransformationId": {
            "Name": "VPL-TransformNewAccountPref",
            "VlocityDataPackType": "VlocityMatchingKeyObject",
            "VlocityMatchingRecordSourceKey": "OmniDataTransform/VPL-TransformNewAccountPref",
            "VlocityRecordSObjectType": "OmniDataTransform"
        },
        "OutputCreationSequence": 1,
        "OutputFieldName": "UpdatedAccountPref|7:CategoryId",
        "OutputObjectName": "json",
        "VlocityDataPackType": "SObject",
        "VlocityRecordSObjectType": "OmniDataTransformItem"
    }
]