{
    "IsActive": true,
    "IsOmniScriptEmbeddable": false,
    "Name": "UpdateConsumerPremiseSuccess",
    "OmniProcessId": {
        "Name": "sfiEnergySelfServiceUpdateConsumerPremises",
        "VlocityDataPackType": "VlocityMatchingKeyObject",
        "VlocityMatchingRecordSourceKey": "OmniProcess/sfiEnergySelfService/UpdateConsumerPremises/Procedure",
        "VlocityRecordSObjectType": "OmniProcess"
    },
    "PropertySetConfig": {
        "additionalOutput": {
            "SSPConsumerPremisesName": "%UpdateConsumerPremise:updatedPremiseName%"
        },
        "disOnTplt": false,
        "executionConditionalFormula": "",
        "label": "ResponseAction1",
        "responseDefaultData": {
        },
        "responseFormat": "JSON",
        "responseJSONNode": "",
        "responseJSONPath": "",
        "returnFullDataJSON": false,
        "returnOnlyAdditionalOutput": true,
        "sendJSONNode": "",
        "sendJSONPath": "",
        "show": null,
        "useFormulas": true,
        "vlcResponseHeaders": {
        }
    },
    "Type": "Response Action",
    "VlocityDataPackType": "SObject",
    "VlocityRecordSObjectType": "OmniProcessElement",
    "VlocityRecordSourceKey": "OmniProcessElement/OmniProcess/sfiEnergySelfService/UpdateConsumerPremises/Procedure/UpdateConsumerPremiseSuccess"
}