{
    "IsActive": true,
    "IsOmniScriptEmbeddable": false,
    "Name": "InitString",
    "OmniProcessId": {
        "Name": "sfiEnergySelfServiceGetPlanDetails",
        "VlocityDataPackType": "VlocityMatchingKeyObject",
        "VlocityMatchingRecordSourceKey": "OmniProcess/sfiEnergySelfService/GetPlanDetails/Procedure",
        "VlocityRecordSObjectType": "OmniProcess"
    },
    "PropertySetConfig": {
        "actionMessage": "",
        "chainOnStep": false,
        "disOnTplt": false,
        "elementValueMap": {
            "Blank": ""
        },
        "executionConditionalFormula": "",
        "failOnStepError": true,
        "failureConditionalFormula": "",
        "label": "SetValues2",
        "responseJSONNode": "ConcatString",
        "responseJSONPath": "Blank",
        "show": null
    },
    "Type": "Set Values",
    "VlocityDataPackType": "SObject",
    "VlocityRecordSObjectType": "OmniProcessElement",
    "VlocityRecordSourceKey": "OmniProcessElement/OmniProcess/sfiEnergySelfService/GetPlanDetails/Procedure/InitString"
}