{
    "Description": "Picklist to let the user select the payment plan",
    "IsActive": true,
    "IsOmniScriptEmbeddable": false,
    "Name": "PaymentPlan",
    "OmniProcessId": {
        "Name": "VPLEnergyCreatePaymentPlan",
        "VlocityDataPackType": "VlocityMatchingKeyObject",
        "VlocityMatchingRecordSourceKey": "OmniProcess/vplEnergy/CreatePaymentPlan/Multi-Language",
        "VlocityRecordSObjectType": "OmniProcess"
    },
    "ParentElementId": {
        "Name": "AccountBalanceDetails",
        "OmniProcessId": {
            "Name": "VPLEnergyCreatePaymentPlan",
            "VlocityDataPackType": "VlocityMatchingKeyObject",
            "VlocityMatchingRecordSourceKey": "OmniProcess/vplEnergy/CreatePaymentPlan/Multi-Language",
            "VlocityRecordSObjectType": "OmniProcess"
        },
        "VlocityDataPackType": "VlocityMatchingKeyObject",
        "VlocityMatchingRecordSourceKey": "OmniProcessElement/OmniProcess/vplEnergy/CreatePaymentPlan/Multi-Language/AccountBalanceDetails",
        "VlocityRecordSObjectType": "OmniProcessElement"
    },
    "ParentElementName": "AccountBalanceDetails",
    "ParentElementType": "Step",
    "PropertySetConfig": {
        "HTMLTemplateId": "",
        "accessibleInFutureSteps": false,
        "conditionType": "Hide if False",
        "controlWidth": 5,
        "controllingField": {
            "element": "",
            "source": "",
            "type": ""
        },
        "disOnTplt": false,
        "help": false,
        "helpText": "",
        "hide": false,
        "inputWidth": 12,
        "label": "sfiEnergyConsoleSelectPaymentPlan",
        "optionSource": {
            "source": "",
            "type": ""
        },
        "options": [
            {
                "name": "AccountBalance",
                "value": "sfiEnergyConsoleAccountBalance"
            },
            {
                "name": "PastDueAmount",
                "value": "sfiEnergyConsolePastDueAmount"
            },
            {
                "name": "Other",
                "value": "sfiEnergyConsoleOther"
            }
        ],
        "readOnly": false,
        "repeat": false,
        "repeatClone": false,
        "required": true,
        "showInputWidth": true
    },
    "Type": "Select",
    "VlocityDataPackType": "SObject",
    "VlocityRecordSObjectType": "OmniProcessElement",
    "VlocityRecordSourceKey": "OmniProcessElement/OmniProcess/vplEnergy/CreatePaymentPlan/Multi-Language/PaymentPlan"
}