[
    {
        "FormulaSequence": 1,
        "GlobalKey": "sfiEnergyConsoleFSCancelAppointmentCustom1670",
        "IsDisabled": false,
        "IsRequiredForUpsert": false,
        "IsUpsertKey": false,
        "Name": "sfiEnergyConsoleFSCancelAppointment",
        "OmniDataTransformationId": {
            "Name": "sfiEnergyConsoleFSCancelAppointment",
            "VlocityDataPackType": "VlocityMatchingKeyObject",
            "VlocityMatchingRecordSourceKey": "OmniDataTransform/sfiEnergyConsoleFSCancelAppointment",
            "VlocityRecordSObjectType": "OmniDataTransform"
        },
        "OutputCreationSequence": 0,
        "OutputFieldName": "Formula",
        "OutputObjectName": "Formula",
        "VlocityDataPackType": "SObject",
        "VlocityRecordSObjectType": "OmniDataTransformItem"
    },
    {
        "GlobalKey": "sfiEnergyConsoleFSCancelAppointmentCustom7639",
        "InputFieldName": "serviceAppointmentId",
        "IsDisabled": false,
        "IsRequiredForUpsert": true,
        "IsUpsertKey": true,
        "Name": "sfiEnergyConsoleFSCancelAppointment",
        "OmniDataTransformationId": {
            "Name": "sfiEnergyConsoleFSCancelAppointment",
            "VlocityDataPackType": "VlocityMatchingKeyObject",
            "VlocityMatchingRecordSourceKey": "OmniDataTransform/sfiEnergyConsoleFSCancelAppointment",
            "VlocityRecordSObjectType": "OmniDataTransform"
        },
        "OutputCreationSequence": 1,
        "OutputFieldName": "Id",
        "OutputObjectName": "ServiceAppointment",
        "VlocityDataPackType": "SObject",
        "VlocityRecordSObjectType": "OmniDataTransformItem"
    },
    {
        "FilterOperator": "=",
        "GlobalKey": "sfiEnergyConsoleFSCancelAppointmentCustom580",
        "IsDisabled": true,
        "IsRequiredForUpsert": false,
        "IsUpsertKey": false,
        "MigrationValue": "FAKEMAPPING",
        "Name": "sfiEnergyConsoleFSCancelAppointment",
        "OmniDataTransformationId": {
            "Name": "sfiEnergyConsoleFSCancelAppointment",
            "VlocityDataPackType": "VlocityMatchingKeyObject",
            "VlocityMatchingRecordSourceKey": "OmniDataTransform/sfiEnergyConsoleFSCancelAppointment",
            "VlocityRecordSObjectType": "OmniDataTransform"
        },
        "OutputCreationSequence": 1,
        "OutputFieldName": "Id",
        "OutputObjectName": "ServiceAppointment",
        "VlocityDataPackType": "SObject",
        "VlocityRecordSObjectType": "OmniDataTransformItem"
    },
    {
        "DefaultValue": "Canceled",
        "GlobalKey": "sfiEnergyConsoleFSCancelAppointmentCustom3494",
        "IsDisabled": false,
        "IsRequiredForUpsert": true,
        "IsUpsertKey": false,
        "Name": "sfiEnergyConsoleFSCancelAppointment",
        "OmniDataTransformationId": {
            "Name": "sfiEnergyConsoleFSCancelAppointment",
            "VlocityDataPackType": "VlocityMatchingKeyObject",
            "VlocityMatchingRecordSourceKey": "OmniDataTransform/sfiEnergyConsoleFSCancelAppointment",
            "VlocityRecordSObjectType": "OmniDataTransform"
        },
        "OutputCreationSequence": 1,
        "OutputFieldName": "Status",
        "OutputObjectName": "ServiceAppointment",
        "VlocityDataPackType": "SObject",
        "VlocityRecordSObjectType": "OmniDataTransformItem"
    },
    {
        "GlobalKey": "sfiEnergyConsoleFSCancelAppointmentCustom4313",
        "InputFieldName": "workOrderId",
        "IsDisabled": false,
        "IsRequiredForUpsert": true,
        "IsUpsertKey": true,
        "Name": "sfiEnergyConsoleFSCancelAppointment",
        "OmniDataTransformationId": {
            "Name": "sfiEnergyConsoleFSCancelAppointment",
            "VlocityDataPackType": "VlocityMatchingKeyObject",
            "VlocityMatchingRecordSourceKey": "OmniDataTransform/sfiEnergyConsoleFSCancelAppointment",
            "VlocityRecordSObjectType": "OmniDataTransform"
        },
        "OutputCreationSequence": 2,
        "OutputFieldName": "Id",
        "OutputObjectName": "WorkOrder",
        "VlocityDataPackType": "SObject",
        "VlocityRecordSObjectType": "OmniDataTransformItem"
    },
    {
        "FilterOperator": "=",
        "GlobalKey": "sfiEnergyConsoleFSCancelAppointmentCustom9034",
        "IsDisabled": true,
        "IsRequiredForUpsert": false,
        "IsUpsertKey": false,
        "MigrationValue": "FAKEMAPPING",
        "Name": "sfiEnergyConsoleFSCancelAppointment",
        "OmniDataTransformationId": {
            "Name": "sfiEnergyConsoleFSCancelAppointment",
            "VlocityDataPackType": "VlocityMatchingKeyObject",
            "VlocityMatchingRecordSourceKey": "OmniDataTransform/sfiEnergyConsoleFSCancelAppointment",
            "VlocityRecordSObjectType": "OmniDataTransform"
        },
        "OutputCreationSequence": 2,
        "OutputFieldName": "Id",
        "OutputObjectName": "WorkOrder",
        "VlocityDataPackType": "SObject",
        "VlocityRecordSObjectType": "OmniDataTransformItem"
    },
    {
        "DefaultValue": "Canceled",
        "GlobalKey": "sfiEnergyConsoleFSCancelAppointmentCustom6076",
        "IsDisabled": false,
        "IsRequiredForUpsert": true,
        "IsUpsertKey": false,
        "Name": "sfiEnergyConsoleFSCancelAppointment",
        "OmniDataTransformationId": {
            "Name": "sfiEnergyConsoleFSCancelAppointment",
            "VlocityDataPackType": "VlocityMatchingKeyObject",
            "VlocityMatchingRecordSourceKey": "OmniDataTransform/sfiEnergyConsoleFSCancelAppointment",
            "VlocityRecordSObjectType": "OmniDataTransform"
        },
        "OutputCreationSequence": 2,
        "OutputFieldName": "Status",
        "OutputObjectName": "WorkOrder",
        "VlocityDataPackType": "SObject",
        "VlocityRecordSObjectType": "OmniDataTransformItem"
    },
    {
        "GlobalKey": "sfiEnergyConsoleFSCancelAppointmentCustom9447",
        "InputFieldName": "caseId",
        "IsDisabled": false,
        "IsRequiredForUpsert": true,
        "IsUpsertKey": true,
        "Name": "sfiEnergyConsoleFSCancelAppointment",
        "OmniDataTransformationId": {
            "Name": "sfiEnergyConsoleFSCancelAppointment",
            "VlocityDataPackType": "VlocityMatchingKeyObject",
            "VlocityMatchingRecordSourceKey": "OmniDataTransform/sfiEnergyConsoleFSCancelAppointment",
            "VlocityRecordSObjectType": "OmniDataTransform"
        },
        "OutputCreationSequence": 3,
        "OutputFieldName": "Id",
        "OutputObjectName": "Case",
        "VlocityDataPackType": "SObject",
        "VlocityRecordSObjectType": "OmniDataTransformItem"
    },
    {
        "FilterOperator": "=",
        "GlobalKey": "sfiEnergyConsoleFSCancelAppointmentCustom8954",
        "IsDisabled": true,
        "IsRequiredForUpsert": false,
        "IsUpsertKey": false,
        "MigrationValue": "FAKEMAPPING",
        "Name": "sfiEnergyConsoleFSCancelAppointment",
        "OmniDataTransformationId": {
            "Name": "sfiEnergyConsoleFSCancelAppointment",
            "VlocityDataPackType": "VlocityMatchingKeyObject",
            "VlocityMatchingRecordSourceKey": "OmniDataTransform/sfiEnergyConsoleFSCancelAppointment",
            "VlocityRecordSObjectType": "OmniDataTransform"
        },
        "OutputCreationSequence": 3,
        "OutputFieldName": "Id",
        "OutputObjectName": "Case",
        "VlocityDataPackType": "SObject",
        "VlocityRecordSObjectType": "OmniDataTransformItem"
    },
    {
        "DefaultValue": "Canceled",
        "GlobalKey": "sfiEnergyConsoleFSCancelAppointmentCustom3959",
        "IsDisabled": false,
        "IsRequiredForUpsert": true,
        "IsUpsertKey": false,
        "Name": "sfiEnergyConsoleFSCancelAppointment",
        "OmniDataTransformationId": {
            "Name": "sfiEnergyConsoleFSCancelAppointment",
            "VlocityDataPackType": "VlocityMatchingKeyObject",
            "VlocityMatchingRecordSourceKey": "OmniDataTransform/sfiEnergyConsoleFSCancelAppointment",
            "VlocityRecordSObjectType": "OmniDataTransform"
        },
        "OutputCreationSequence": 3,
        "OutputFieldName": "Status",
        "OutputObjectName": "Case",
        "VlocityDataPackType": "SObject",
        "VlocityRecordSObjectType": "OmniDataTransformItem"
    }
]