{
    "AuthorName": "Vlocity",
    "ClonedFromOmniUiCardKey": "",
    "DataSourceConfig": {
        "contextVariables": [
            {
                "id": 6,
                "name": "Parent.cartId",
                "val": "8015g000000cABAAA2"
            },
            {
                "id": 38,
                "name": "Parent.ObjectType",
                "val": "Order"
            },
            {
                "id": 7,
                "name": "Parent.pricelistId",
                "val": ""
            }
        ],
        "orderBy": {
            "isReverse": false,
            "name": ""
        },
        "type": "IntegrationProcedures",
        "value": {
            "dsDelay": "",
            "inputMap": {
                "ObjectType": "{Parent.ObjectType}",
                "cartId": "{Parent.cartId}",
                "pricelistId": "{Parent.pricelistId}"
            },
            "ipMethod": "CPQ_GetGlobalHeaderDetails",
            "resultVar": "[\"response\"]",
            "vlocityAsync": false
        }
    },
    "Description": "",
    "IsTrackingEnabled": false,
    "Name": "cpqGlobalHeader",
    "Namespace": "",
    "OmniUiCardKey": "cpqGlobalHeader/Vlocity/5/1658208749791",
    "OmniUiCardType": "Child",
    "OverrideKey": "",
    "PropertySetConfig": "cpqGlobalHeader.json",
    "SampleDataSourceResponse": "{\"response\":{\"ApprovalRequired\":true,\"AccountId\":\"0015g00000HIfoRAAT\",\"Id\":\"8015g000000cABAAA2\",\"PriceListId\":\"a3D5g000000ojWVEAY\",\"PriceListName\":\"COMMS_CPQ_PriceList_0\",\"effectivedate\":\"2021-07-22\",\"AccountName\":\"Apple\"}}",
    "StylingConfiguration": "{\"customStyles\":\".values{\\n    font-size: 14px;\\n    line-height: 21px;\\n    color: #080707;\\n    margin: 2px 0px;\\n    text-overflow: ellipsis\\n}\\n\\n.title-text{\\n    font-size: 12px;\\n    line-height: 18px;\\n    color: #3E3E3C;\\n    margin: 2px 0px;\\n}\\n\\n.account-title{\\n    font-size: 12px;\\n    line-height: 18px;\\n    color: #3E3E3C;\\n    margin: 2px 0px;\\n    width: 46px;\\n}\\n\\n.account{\\n    font-size: 14px;\\n    line-height: 21px;\\n    color: #1073D0;\\n    margin: 2px 0px;\\n}\\n\\n\\n.status-approval-box{\\n    width: fit-content;\\n    max-width: 12%;\\n}\\n\\n.account-box{\\n    width: fit-content;\\n    max-width: 25%;\\n}\\n.object-id-text{\\n    max-width: 100%;\\n    display: -webkit-box;\\n    -webkit-line-clamp: 2;\\n    -webkit-box-orient: vertical;\\n    overflow: hidden;\\n}\\n\\n.account-box .slds-action_text{\\n    max-width: 100%;\\n    display: -webkit-box;\\n    -webkit-line-clamp: 2;\\n    -webkit-box-orient: vertical;\\n    overflow: hidden;\\n}\\n\\n.account-box-mobile .slds-action_text{\\n    max-width: 100%;\\n    display: -webkit-box;\\n    -webkit-line-clamp: 2;\\n    -webkit-box-orient: vertical;\\n    overflow: hidden;\\n}\\n\\n.fit-content-style{\\n    width:fit-content;\\n}\\n\\n.custom-btn{\\n    width:fit-content;\\n}\\n\\n.custom-btn .slds-button{\\n    border-radius: 0px;\\n    margin-right: -1px;\\n}\\n\\n.btn-block{\\n    margin-left:auto;\\n    width:fit-content;\\n}\\n\\n.price-field{\\n    margin-left:auto;\\n}\\n\\n.icon-style{\\n    width: fit-content;\\n    padding-right: 10px;\\n}\\n\\n.updateApiCSS{\\n    display: none;\\n}\\n\\n.mobile-state {\\n    display: initial;\\n}\\n\\n.desktop-state {\\n    display: none;\\n}\\n\\n\\n@media (min-width: 1024px) {\\n  .mobile-state {\\n    display: none;\\n  }\\n  .desktop-state {\\n  \\tdisplay: initial;\\n  }\\n}\\n\"}",
    "UniqueName": "",
    "VersionNumber": 3,
    "VlocityDataPackType": "SObject",
    "VlocityRecordSObjectType": "OmniUiCard",
    "VlocityRecordSourceKey": "OmniUiCard/cpqGlobalHeader"
}