{
    "IsActive": true,
    "IsOmniScriptEmbeddable": false,
    "Name": "DecryptOrderNumber",
    "OmniProcessId": {
        "Name": "VEEDigitalCreateAccountAndCart",
        "VlocityDataPackType": "VlocityMatchingKeyObject",
        "VlocityMatchingRecordSourceKey": "OmniProcess/VEE/DigitalCreateAccountAndCart/Procedure",
        "VlocityRecordSObjectType": "OmniProcess"
    },
    "PropertySetConfig": {
        "actionMessage": "",
        "additionalChainableResponse": {
        },
        "additionalInput": {
            "encryptedString": "%CreateCart:orderNumber%"
        },
        "additionalOutput": {
        },
        "chainOnStep": false,
        "disOnTplt": false,
        "executionConditionalFormula": "",
        "failOnStepError": true,
        "failureConditionalFormula": "",
        "failureResponse": {
            "ErrorMessage": "VEEDigitalCreateAccountAndCart:DecryptOrderNumber Failed to encrypt the Order Number"
        },
        "label": "RemoteAction2",
        "remoteClass": "VEEAppHandler",
        "remoteMethod": "decryptIfNecessary",
        "remoteOptions": {
        },
        "responseJSONNode": "",
        "responseJSONPath": "",
        "returnOnlyAdditionalOutput": false,
        "returnOnlyFailureResponse": false,
        "sendJSONNode": "",
        "sendJSONPath": "",
        "sendOnlyAdditionalInput": true,
        "show": null,
        "useFormulas": true
    },
    "Type": "Remote Action",
    "VlocityDataPackType": "SObject",
    "VlocityRecordSObjectType": "OmniProcessElement",
    "VlocityRecordSourceKey": "OmniProcessElement/OmniProcess/VEE/DigitalCreateAccountAndCart/Procedure/DecryptOrderNumber"
}