{
    "remoteOptions": {
        "useContinuation": false,
        "useQueueableApexRemoting": false,
        "vlcClass": "%vlocity_namespace%.DefaultDROmniScriptIntegration"
    },
    "request": {
        "bundleName": "VPL-UpdateAssetAfterCallout",
        "objectList": {
            "AccountDisplayName": "Dun Dunks",
            "AccountIdRedirection": "0013h00000KSMP7AAP",
            "AgreementIdList": [
                "1500011384",
                "1500011385",
                "1500011386"
            ],
            "AgreementMessageList": [
                "Contract 1500011384 created for installation 800012984 (move-in date 04.05.2019) Move-in document 100011516 created.Contract 1500011385 created for installation 800012987 (move-in date 2020-09-18 10:38:52.239503).",
                "Contract 1500011384 created for installation 800012985 (move-in date 2020-09-18 10:38:52.239503) Move-in document 100011516 created.Contract 1500011385 created for installation 800012987 (move-in date 2020-09-18 10:38:52.239503).",
                "Contract 1500011384 created for installation 800012986 (move-in date 04.05.2019) Move-in document 100011516 created.Contract 1500011385 created for installation 800012987 (move-in date 2020-09-18 10:38:52.239503)."
            ],
            "AttrCategory": [
                {
                    "CategoryCode": "COST",
                    "CategoryId": "a0O3h000001MyF9EAK"
                },
                {
                    "CategoryCode": "PURCHASE_CRITERIA_COST",
                    "CategoryId": "a0O3h000001MytJEAS"
                },
                {
                    "CategoryCode": "OUTAGE_NOTIFICATIONS",
                    "CategoryId": "a0O3h000001Mfw4EAC"
                },
                {
                    "CategoryCode": "OFFERS_PROMOTIONS",
                    "CategoryId": "a0O3h000001Mfw5EAC"
                },
                {
                    "CategoryCode": "WORKORDER_NOTIFICATIONS",
                    "CategoryId": "a0O3h000001Mfw6EAC"
                },
                {
                    "CategoryCode": "BILL_NOTIFICATIONS",
                    "CategoryId": "a0O3h000001MfvkEAC"
                },
                {
                    "CategoryCode": "PAYMENT_REMINDERS",
                    "CategoryId": "a0O3h000001MfvlEAC"
                },
                {
                    "CategoryCode": "DNC_FROM",
                    "CategoryId": "a0O3h000001MfvmEAC"
                },
                {
                    "CategoryCode": "DNC_TO",
                    "CategoryId": "a0O3h000001Mg0HEAS"
                }
            ],
            "AttributeAccountId": "0013h00000KSMP7AAP",
            "AvailableProductMaxRowSelection": "Multiple",
            "AvialbleProductsColumns": [
                {
                    "fieldName": "ProdName",
                    "label": "Product Name"
                },
                {
                    "fieldName": "ProdFamily",
                    "label": "Product Family"
                },
                {
                    "fieldName": "ProdCategory",
                    "label": "Service Type"
                },
                {
                    "fieldName": "ProdDescription",
                    "label": "Description"
                }
            ],
            "BankPaymentDetails": null,
            "BillingAccountId": "0013h00000KSMPCAA5",
            "BillingAccountRecTypeId": "0123h000000jV4IAAU",
            "BillingAccountRecordType": "Billing",
            "BillingPreferences": {
                "APaymentType": "Prepaid",
                "AutoPay": "No",
                "BillNotification": "Yes",
                "MailingAddres": null,
                "MailingAddresss": null,
                "MailingCity": null,
                "MailingCountry": null,
                "MailingState": null,
                "MailingStreet": null,
                "MailingZipCode": null,
                "OffersPromotions": "No",
                "OutageNotification": "No",
                "PaymentNotification": "Yes",
                "WorkOrderNotification": "Yes"
            },
            "BusinessAccountId": "0013h00000KSMP7AAP",
            "BusinessAccountRecTypeId": "0123h000000jV4HAAU",
            "BusinessAccountRecordType": "Business",
            "Category": {
                "BillNotifications": {
                    "CategoryCode": "BILL_NOTIFICATIONS",
                    "CategoryId": "a0O3h000001MfvkEAC"
                },
                "DNCFrom": {
                    "CategoryCode": "DNC_FROM",
                    "CategoryId": "a0O3h000001MfvmEAC"
                },
                "DNCTo": {
                    "CategoryCode": "DNC_TO",
                    "CategoryId": "a0O3h000001Mg0HEAS"
                },
                "OffersPromotions": {
                    "CategoryCode": "OFFERS_PROMOTIONS",
                    "CategoryId": "a0O3h000001Mfw5EAC"
                },
                "OutageNotifications": {
                    "CategoryCode": "OUTAGE_NOTIFICATIONS",
                    "CategoryId": "a0O3h000001Mfw4EAC"
                },
                "PaymentReminders": {
                    "CategoryCode": "PAYMENT_REMINDERS",
                    "CategoryId": "a0O3h000001MfvlEAC"
                },
                "WorkorderNotifications": {
                    "CategoryCode": "WORKORDER_NOTIFICATIONS",
                    "CategoryId": "a0O3h000001Mfw6EAC"
                }
            },
            "ChoosePaymentMethod": null,
            "Confirmation": {
            },
            "ContactIdRedirection": "0033h00000E4JPTAA3",
            "CustomerSelection": {
                "AccountType": "Business",
                "BillingDetails": {
                },
                "BusinessAccountName": "Fun Fury",
                "ConNameError": null,
                "ExistingAccount-Block": null,
                "GetCustomer-Block": null,
                "MoveInDate": "2020-09-18T18:30:00.000Z",
                "MoveInDateFormula": true,
                "MoveInMessage": true,
                "MsgInvalidExistingAccount": null,
                "MsgInvalidParentAccount": null,
                "NewAccountNeeded": null,
                "NewCustomer": "Yes",
                "NewCustomerDetails": {
                    "CustomerDOB": "09/17/2020",
                    "CustomerEmail": "test@tt.co",
                    "CustomerFirstName": "Dun",
                    "CustomerLastName": "Dunks",
                    "CustomerPhone": "0767887878",
                    "DOBFormula": true,
                    "DOBMsg": true,
                    "DriverLicense": null,
                    "IdentificationType": "TaxID",
                    "SSN": null,
                    "TaxId": "234342343"
                },
                "ParentAccount-Block": {
                    "ParentAccount": null
                },
                "TaxDetails": {
                    "ExemptionEndDate": null,
                    "ExemptionPercentage": null,
                    "ExemptionStartDate": null
                }
            },
            "DRId_Account": "0013h00000KSMP7AAP",
            "DRId_Contact": "0033h00000E4JPTAA3",
            "ERPAccountID__c": 6011110,
            "ERP_Contract_ID__c": 2334455,
            "FML_Today": "2020-09-17T18:30:00.000Z",
            "IntegrationType": "JSON",
            "OmniscriptType": "Move_In",
            "PaymentDetails": null,
            "PreConfirm": {
                "Confirm": "Yes"
            },
            "PremisesDisplayName": "Coventry premise",
            "Products": {
                "ElectricityProduct": [
                    {
                        "Id": "01t3h000001Ck7WAAS",
                        "Name": "Day/Night Tariff",
                        "ProductCode": "001"
                    },
                    {
                        "Id": "01t3h000001Ck7gAAC",
                        "Name": "Night Display Tariff",
                        "ProductCode": "003"
                    },
                    {
                        "Id": "01t3h000001Ck7bAAC",
                        "Name": "High Voltage Tariff",
                        "ProductCode": "002"
                    }
                ],
                "GasProduct": [
                    {
                        "Id": "01t3h000001Ck7lAAC",
                        "Name": "Turn Off Order",
                        "ProductCode": "004"
                    },
                    {
                        "Id": "01t3h000001Ck7qAAC",
                        "Name": "Regulated Gas Rate",
                        "ProductCode": "REG-GAS-1"
                    }
                ],
                "WaterProduct": [
                    {
                        "Id": "01t3h000001Ck7vAAC",
                        "Name": "Water",
                        "ProductCode": "water"
                    }
                ]
            },
            "RecordType": [
                {
                    "Id": "0123h000000jV4JAAU",
                    "Name": "Service"
                }
            ],
            "SAPIntegrated": "Yes",
            "SObjectName": "Account",
            "SelectPremises": {
                "ExistingAccountExistingPremisesId": null,
                "NewAccountPremises": null,
                "PremiseError": null,
                "ServiceLocation-Block": {
                    "PremCity": "Kolkata",
                    "PremCountry": "India",
                    "PremId": "a3X3h0000006OviEAE",
                    "PremPostalCode": "700059",
                    "PremState": "West Bengal",
                    "PremiseName": "Coventry premise",
                    "PremiseNumber": "PR70001",
                    "PremiseStreetAddress": "Akshara Lotus Garden Coevtry",
                    "ServiceLocation": "Coventry premise"
                }
            },
            "SelectService": [
                {
                    "InventoryItemId": "a2O3h000000hrDfEAI",
                    "PremiseNumber": "PR70001",
                    "PremisesId": "a3X3h0000006OviEAE",
                    "ServicePointId": "a4P3h000000VDn6EAG",
                    "ServicePointName": "Coventry Day Night Electricity",
                    "ServicePointNumber": "SR50004",
                    "ServiceType": "Electricity",
                    "Status": "Connected"
                },
                {
                    "InventoryItemId": "a2O3h000000hrDaEAI",
                    "PremiseNumber": "PR70001",
                    "PremisesId": "a3X3h0000006OviEAE",
                    "ServicePointId": "a4P3h00000059waEAA",
                    "ServicePointName": "Coventry Gas",
                    "ServicePointNumber": "SR50003",
                    "ServiceType": "Gas",
                    "Status": "Connected"
                },
                {
                    "InventoryItemId": "a2O3h000000hrDVEAY",
                    "PremiseNumber": "PR70001",
                    "PremisesId": "a3X3h0000006OviEAE",
                    "ServicePointId": "a4P3h00000059wGEAQ",
                    "ServicePointName": "Coventry Electricity",
                    "ServicePointNumber": "SR50001",
                    "ServiceType": "Electricity",
                    "Status": "Connected"
                },
                {
                    "InventoryItemId": "a2O3h000000hrDQEAY",
                    "PremiseNumber": "PR70001",
                    "PremisesId": "a3X3h0000006OviEAE",
                    "ServicePointId": "a4P3h00000059wHEAQ",
                    "ServicePointName": "Coventry Water",
                    "ServicePointNumber": "SR50002",
                    "ServiceType": "Water",
                    "Status": "Connected"
                }
            ],
            "SelectServicePoints": [
                {
                    "InventoryItemId": "a2O3h000000hrDfEAI",
                    "PremiseNumber": "PR70001",
                    "PremisesId": "a3X3h0000006OviEAE",
                    "ServicePointId": "a4P3h000000VDn6EAG",
                    "ServicePointName": "Coventry Day Night Electricity",
                    "ServicePointNumber": "SR50004",
                    "ServiceType": "Electricity",
                    "Status": "Connected"
                },
                {
                    "InventoryItemId": "a2O3h000000hrDaEAI",
                    "PremiseNumber": "PR70001",
                    "PremisesId": "a3X3h0000006OviEAE",
                    "ServicePointId": "a4P3h00000059waEAA",
                    "ServicePointName": "Coventry Gas",
                    "ServicePointNumber": "SR50003",
                    "ServiceType": "Gas",
                    "Status": "Connected"
                },
                {
                    "InventoryItemId": "a2O3h000000hrDVEAY",
                    "PremiseNumber": "PR70001",
                    "PremisesId": "a3X3h0000006OviEAE",
                    "ServicePointId": "a4P3h00000059wGEAQ",
                    "ServicePointName": "Coventry Electricity",
                    "ServicePointNumber": "SR50001",
                    "ServiceType": "Electricity",
                    "Status": "Connected"
                },
                {
                    "InventoryItemId": "a2O3h000000hrDQEAY",
                    "PremiseNumber": "PR70001",
                    "PremisesId": "a3X3h0000006OviEAE",
                    "ServicePointId": "a4P3h00000059wHEAQ",
                    "ServicePointName": "Coventry Water",
                    "ServicePointNumber": "SR50002",
                    "ServiceType": "Water",
                    "Status": "Connected"
                }
            ],
            "SelectTypeofService": {
                "SelectServicePoint": null,
                "SelectServicePoints": [
                    {
                        "InventoryItemId": "a2O3h000000hrDfEAI",
                        "PremiseNumber": "PR70001",
                        "PremisesId": "a3X3h0000006OviEAE",
                        "ProductId": "01t3h000001Ck7gAAC",
                        "ProductName": "Night Display Tariff",
                        "ServicePointId": "a4P3h000000VDn6EAG",
                        "ServicePointName": "Coventry Day Night Electricity",
                        "ServicePointNumber": "SR50004",
                        "ServiceType": "Electricity",
                        "Status": "Connected",
                        "originalIndex": "0"
                    },
                    {
                        "InventoryItemId": "a2O3h000000hrDVEAY",
                        "PremiseNumber": "PR70001",
                        "PremisesId": "a3X3h0000006OviEAE",
                        "ProductId": "01t3h000001Ck7WAAS",
                        "ProductName": "Day/Night Tariff",
                        "ServicePointId": "a4P3h00000059wGEAQ",
                        "ServicePointName": "Coventry Electricity",
                        "ServicePointNumber": "SR50001",
                        "ServiceType": "Electricity",
                        "Status": "Connected",
                        "originalIndex": "2"
                    },
                    {
                        "InventoryItemId": "a2O3h000000hrDaEAI",
                        "PremiseNumber": "PR70001",
                        "PremisesId": "a3X3h0000006OviEAE",
                        "ProductId": "01t3h000001Ck7qAAC",
                        "ProductName": "Regulated Gas Rate",
                        "ServicePointId": "a4P3h00000059waEAA",
                        "ServicePointName": "Coventry Gas",
                        "ServicePointNumber": "SR50003",
                        "ServiceType": "Gas",
                        "Status": "Connected",
                        "originalIndex": "1"
                    },
                    {
                        "InventoryItemId": "a2O3h000000hrDQEAY",
                        "PremiseNumber": "PR70001",
                        "PremisesId": "a3X3h0000006OviEAE",
                        "ProductId": "01t3h000001Ck7vAAC",
                        "ProductName": "Water",
                        "ServicePointId": "a4P3h00000059wHEAQ",
                        "ServicePointName": "Coventry Water",
                        "ServicePointNumber": "SR50002",
                        "ServiceType": "Water",
                        "Status": "Connected",
                        "originalIndex": "3"
                    }
                ],
                "ServicePointsFormula": 4
            },
            "SelectedPremises": "a3X3h0000006OviEAE",
            "SelectedServiceData": [
                {
                    "InventoryItemId": "a2O3h000000hrDfEAI",
                    "PremiseNumber": "PR70001",
                    "PremisesId": "a3X3h0000006OviEAE",
                    "ProductId": "01t3h000001Ck7gAAC",
                    "ProductName": "Night Display Tariff",
                    "ServicePointId": "a4P3h000000VDn6EAG",
                    "ServicePointName": "Coventry Day Night Electricity",
                    "ServicePointNumber": "SR50004",
                    "ServiceType": "Electricity",
                    "Status": "Connected",
                    "originalIndex": "0"
                },
                {
                    "InventoryItemId": "a2O3h000000hrDVEAY",
                    "PremiseNumber": "PR70001",
                    "PremisesId": "a3X3h0000006OviEAE",
                    "ProductId": "01t3h000001Ck7WAAS",
                    "ProductName": "Day/Night Tariff",
                    "ServicePointId": "a4P3h00000059wGEAQ",
                    "ServicePointName": "Coventry Electricity",
                    "ServicePointNumber": "SR50001",
                    "ServiceType": "Electricity",
                    "Status": "Connected",
                    "originalIndex": "2"
                },
                {
                    "InventoryItemId": "a2O3h000000hrDaEAI",
                    "PremiseNumber": "PR70001",
                    "PremisesId": "a3X3h0000006OviEAE",
                    "ProductId": "01t3h000001Ck7qAAC",
                    "ProductName": "Regulated Gas Rate",
                    "ServicePointId": "a4P3h00000059waEAA",
                    "ServicePointName": "Coventry Gas",
                    "ServicePointNumber": "SR50003",
                    "ServiceType": "Gas",
                    "Status": "Connected",
                    "originalIndex": "1"
                },
                {
                    "InventoryItemId": "a2O3h000000hrDQEAY",
                    "PremiseNumber": "PR70001",
                    "PremisesId": "a3X3h0000006OviEAE",
                    "ProductId": "01t3h000001Ck7vAAC",
                    "ProductName": "Water",
                    "ServicePointId": "a4P3h00000059wHEAQ",
                    "ServicePointName": "Coventry Water",
                    "ServicePointNumber": "SR50002",
                    "ServiceType": "Water",
                    "Status": "Connected",
                    "originalIndex": "3"
                }
            ],
            "SelectedServiceMaxRow": "",
            "ServiceAccountId": "0013h00000KSMPHAA5",
            "ServiceAccountPremisesColumns": [
                {
                    "fieldName": "Checked",
                    "label": ""
                },
                {
                    "fieldName": "AccountName",
                    "label": "Account Name"
                },
                {
                    "fieldName": "PremisesName",
                    "label": "Premise Address"
                }
            ],
            "ServiceAccountPremisesMaxRowSelection": "Single",
            "ServiceAccountRecTypeId": "0123h000000jV4JAAU",
            "ServiceAccountRecordType": "Service",
            "ServicePointsColumns": [
                {
                    "fieldName": "ServicePointName",
                    "label": "Service Point Name"
                },
                {
                    "fieldName": "ServiceType",
                    "label": "Service Type"
                },
                {
                    "fieldName": "SelectProduct",
                    "label": "Select Product"
                }
            ],
            "ServicePointsColumnsConfirm": [
                {
                    "fieldName": "ServicePointName",
                    "label": "Service Point Name"
                },
                {
                    "fieldName": "ServiceType",
                    "label": "Service Type"
                },
                {
                    "fieldName": "ProductName",
                    "label": "Select Product"
                }
            ],
            "ServicePointsError": null,
            "ServicePremises": null,
            "createResidentialAccount_Msg": "Contract created in SAP successfully..!",
            "timeStamp": "2020-09-18T10:36:54.670Z",
            "userCurrencyCode": "USD",
            "userId": "0053h000002WfuuAAC",
            "userName": "express_org_sebanti@org.dev",
            "userProfile": "System Administrator",
            "userTimeZone": "-420",
            "vlcTimeTracking": {
                "BankPaymentDetails": 0,
                "BillingPreferences": 13193,
                "ChoosePaymentMethod": 0,
                "CreateBankAccountPaymentMethod": 0,
                "CreateCreditCardPaymentMethod": 0,
                "CustomerSelection": 52481,
                "DR-GetProducts": 1449,
                "DRCreatServiceAccount": 1545,
                "DRCreateBillingAccount": 1448,
                "DRCreateBusinessAccount": 1714,
                "DRCreateConsumerAccount": 0,
                "DRExtractAttrCategory": 696,
                "DRExtractBussinessAccountRecId": 745,
                "DRFetchBillingAccountRecTypeId": 1232,
                "DRFetchDesiredRecordType": 1196,
                "DRFetchServiceAccountRecTypeId": 653,
                "DRInsertContact": 1737,
                "DRTransformAttrCategory": 1617,
                "DRUpdateCosnumerBusinessAccount": 1160,
                "ExtractServiceAccountPremises": 0,
                "GetPremServicePoints": 1160,
                "OmniScriptSessionToken": "d022ca4d-ada9-4afd-a3a1-010578758df3",
                "PaymentDetails": 0,
                "PreConfirm": 6394,
                "SVBusinessAccountRecTypeId": 60,
                "SVDisplayData": 54,
                "SVServiceAccountRecTypeId": 110,
                "SVSetAttributeAccountValues": 138,
                "SelectPremises": 7122,
                "SelectTypeofService": 9447,
                "ServicePointsError": 0,
                "SetBillingAccountId": 66,
                "SetBusinessAccountId": 80,
                "SetCustomLWCValues": 208,
                "SetDefaultValues": 175,
                "SetPremisesBusinessAccountRecTypeId": 123,
                "SetRedirectionIdValues": 181,
                "SetServiceAccountId": 176,
                "SetServicePointVal": 75,
                "VIPCreateBusinessPartner": 3871,
                "VIPCreateBusinessPartner_NonSAP": 0,
                "VIPCreateContractAccount": 1183,
                "VIPCreateContractAccount_NonSAP": 0,
                "VIPMoveInPost": 3607
            }
        }
    },
    "response": {
        "error": "Required fields are missing: Asset Name"
    }
}