{
    "premiseInfo": [
        {
            "accountrecordType": "Service",
            "premiseAccountId": "0014x00001B9XH0AAN",
            "premiseAddress": "112 Ocean Avenue , Amityville , NY , 11701",
            "premiseCity": "Amityville",
            "premiseCountry": "United States",
            "premiseName": "112 Ocean Avenue, Amityville,NY,11701,United States",
            "premisePostalCode": "11701",
            "premiseState": "NY",
            "premiseStreet": "112 Ocean Avenue",
            "premisesId": "a3B4x000000PLnFEAW"
        },
        {
            "accountrecordType": "Service",
            "premiseAccountId": "0014x00001B9dzpAAB",
            "premiseAddress": "112 Ocean Avenue , Amityville , NY , 11701",
            "premiseCity": "Amityville",
            "premiseCountry": "United States",
            "premiseName": "112 Ocean Avenue, Amityville,NY,11701,United States",
            "premisePostalCode": "11701",
            "premiseState": "NY",
            "premiseStreet": "112 Ocean Avenue",
            "premisesId": "a3B4x000000PLnFEAW"
        }
    ]
}