{
    "IsActive": true,
    "IsOmniScriptEmbeddable": false,
    "Name": "SVTodayDate",
    "OmniProcessId": {
        "Name": "VPL-UpdateMoveOut",
        "VlocityDataPackType": "VlocityMatchingKeyObject",
        "VlocityMatchingRecordSourceKey": "OmniProcess/VPL/UpdateMoveOut/Procedure",
        "VlocityRecordSObjectType": "OmniProcess"
    },
    "PropertySetConfig": {
        "actionMessage": "",
        "chainOnStep": false,
        "disOnTplt": false,
        "elementValueMap": {
            "TodayDate": "=TODAY()"
        },
        "executionConditionalFormula": "",
        "failOnStepError": true,
        "failureConditionalFormula": "",
        "label": "SetValues2",
        "responseJSONNode": "",
        "responseJSONPath": "",
        "show": null
    },
    "Type": "Set Values",
    "VlocityDataPackType": "SObject",
    "VlocityRecordSObjectType": "OmniProcessElement",
    "VlocityRecordSourceKey": "OmniProcessElement/OmniProcess/VPL/UpdateMoveOut/Procedure/SVTodayDate"
}